ctf_orchestra/challenge.py
ctf_orchestra/config.py
ctf_orchestra/ctf.py
ctf_orchestra/main.py
ctf_orchestra/utils/state.py
ctf_orchestra/utils/themes.py
ctf_orchestra-0.1.0.dist-info/entry_points.txt
ctf_orchestra-0.1.0.dist-info/METADATA
ctf_orchestra-0.1.0.dist-info/WHEEL
ctf_orchestra-0.1.0.dist-info/RECORD
