Metadata-Version: 2.4
Name: ctf-orchestra
Version: 0.1.0
Summary: A CLI for streamlining workflows for Capture-The-Flag players, including tools for file management and environment interaction.
License: MIT
Author: Owen Tam
Author-email: owenhwtam@gmail.com
Requires-Python: >=3.12
Classifier: License :: OSI Approved :: MIT License
Classifier: Programming Language :: Python :: 3
Classifier: Programming Language :: Python :: 3.12
Classifier: Programming Language :: Python :: 3.13
Classifier: Programming Language :: Python :: 3.14
Requires-Dist: argcomplete (==3.6.2)
Requires-Dist: art (==6.5)
Requires-Dist: astroid (==3.3.11)
Requires-Dist: click (==8.2.1)
Requires-Dist: colorama (==0.4.6)
Requires-Dist: dill (==0.4.0)
Requires-Dist: isort (==6.0.1)
Requires-Dist: markdown-it-py (==4.0.0)
Requires-Dist: mccabe (==0.7.0)
Requires-Dist: mdurl (==0.1.2)
Requires-Dist: packaging (==25.0)
Requires-Dist: platformdirs (==4.4.0)
Requires-Dist: pygments (==2.19.2)
Requires-Dist: python-dotenv (==1.1.1)
Requires-Dist: rich (==14.1.0)
Requires-Dist: shellingham (==1.5.4)
Requires-Dist: tomlkit (==0.13.3)
Requires-Dist: typer (==0.16.1)
Requires-Dist: typing-extensions (==4.14.1)
Requires-Dist: userpath (==1.9.2)
